happtiq_commons_gen_ai/__init__.py
happtiq_commons_gen_ai/chatgpt_api_service.py
happtiq_commons_gen_ai/gemini_service.py
kaan_trial1-0.0.1.dist-info/METADATA
kaan_trial1-0.0.1.dist-info/WHEEL
kaan_trial1-0.0.1.dist-info/top_level.txt
kaan_trial1-0.0.1.dist-info/RECORD
