Metadata-Version: 2.1
Name: kaan_trial1
Version: 0.0.1
Requires-Python: >=3.9
Requires-Dist: google-cloud-aiplatform
Requires-Dist: openai
Provides-Extra: dev
Requires-Dist: pytest; extra == "dev"
Requires-Dist: pytest-mock; extra == "dev"
